check_netscaler/__init__.py
check_netscaler/__main__.py
check_netscaler/cli.py
check_netscaler/constants.py
check_netscaler/client/__init__.py
check_netscaler/client/exceptions.py
check_netscaler/client/nitro.py
check_netscaler/client/session.py
check_netscaler/commands/__init__.py
check_netscaler/commands/base.py
check_netscaler/commands/debug.py
check_netscaler/commands/hastatus.py
check_netscaler/commands/hwinfo.py
check_netscaler/commands/interfaces.py
check_netscaler/commands/license.py
check_netscaler/commands/matches.py
check_netscaler/commands/nsconfig.py
check_netscaler/commands/ntp.py
check_netscaler/commands/perfdata.py
check_netscaler/commands/servicegroup.py
check_netscaler/commands/sslcert.py
check_netscaler/commands/staserver.py
check_netscaler/commands/state.py
check_netscaler/commands/threshold.py
check_netscaler/output/__init__.py
check_netscaler/output/nagios.py
check_netscaler/utils/__init__.py
check_netscaler-2.2.0.dist-info/licenses/LICENSE
check_netscaler-2.2.0.dist-info/METADATA
check_netscaler-2.2.0.dist-info/WHEEL
check_netscaler-2.2.0.dist-info/entry_points.txt
check_netscaler-2.2.0.dist-info/top_level.txt
check_netscaler-2.2.0.dist-info/RECORD
