Metadata-Version: 2.4
Name: check_netscaler
Version: 2.2.0
Summary: Nagios/Icinga monitoring plugin for Citrix NetScaler ADC using NITRO REST API
Author-email: slauger <slauger@users.noreply.github.com>
License: MIT
Project-URL: Homepage, https://github.com/slauger/check_netscaler
Project-URL: Repository, https://github.com/slauger/check_netscaler
Project-URL: Issues, https://github.com/slauger/check_netscaler/issues
Keywords: nagios,icinga,monitoring,netscaler,citrix,adc
Classifier: Development Status :: 2 - Pre-Alpha
Classifier: Intended Audience :: System Administrators
Classifier: License :: OSI Approved :: MIT License
Classifier: Programming Language :: Python :: 3
Classifier: Programming Language :: Python :: 3.8
Classifier: Programming Language :: Python :: 3.9
Classifier: Programming Language :: Python :: 3.10
Classifier: Programming Language :: Python :: 3.11
Classifier: Programming Language :: Python :: 3.12
Classifier: Topic :: System :: Monitoring
Requires-Python: >=3.8
License-File: LICENSE
Requires-Dist: requests>=2.31.0
Provides-Extra: dev
Requires-Dist: pytest>=7.4.0; extra == "dev"
Requires-Dist: pytest-cov>=4.1.0; extra == "dev"
Requires-Dist: pytest-mock>=3.11.0; extra == "dev"
Requires-Dist: black>=23.7.0; extra == "dev"
Requires-Dist: ruff>=0.0.285; extra == "dev"
Requires-Dist: mypy>=1.5.0; extra == "dev"
Requires-Dist: types-requests>=2.31.0; extra == "dev"
Dynamic: license-file
